automateimageclassification/__init__.py
automateimageclassification/main.py
automateimageclassification/predict.py
automateimageclassification/train_engine.py
automateimageclassification/com_in_ineuron_ai_utils/__init__.py
automateimageclassification/com_in_ineuron_ai_utils/utils.py
automateimageclassification/utils/__init__.py
automateimageclassification/utils/callbacks.py
automateimageclassification/utils/config.py
automateimageclassification/utils/data_manager.py
automateimageclassification/utils/model.py
automateimageclassification/utils/models_config.py
automateimageclassification-0.2.dist-info/LICENSE
automateimageclassification-0.2.dist-info/LICENSE.txt
automateimageclassification-0.2.dist-info/METADATA
automateimageclassification-0.2.dist-info/WHEEL
automateimageclassification-0.2.dist-info/entry_points.txt
automateimageclassification-0.2.dist-info/top_level.txt
automateimageclassification-0.2.dist-info/RECORD
