Metadata-Version: 2.1
Name: automateimageclassification
Version: 0.2
Summary: Its an auto image classification library
Home-page: https://github.com/funnyPhani/automate-image-classification/
Author: Phani Siginamsetty
Author-email: siginamsettyphani@gmail.com
License: MIT
Keywords: imageseeker,automate-image-classification
Classifier: Development Status :: 3 - Alpha
Classifier: Intended Audience :: Developers
Classifier: Topic :: Software Development :: Build Tools
Classifier: License :: OSI Approved :: MIT License
Classifier: Programming Language :: Python :: 3
Classifier: Programming Language :: Python :: 3.4
Classifier: Programming Language :: Python :: 3.5
Classifier: Programming Language :: Python :: 3.6
License-File: LICENSE
License-File: LICENSE.txt
Requires-Dist: tensorflow (==2.4.1)
Requires-Dist: scipy (==1.6.3)
Requires-Dist: numpy
Requires-Dist: pandas
Requires-Dist: Pillow (==8.3.2)
Requires-Dist: Flask
Requires-Dist: Flask-Cors (==3.0.10)
